microstate/__init__.py
microstate/client.py
microstate/conventions.py
microstate/redis_config.py
microstate/server.py
microstate/server_conventions.py
microstate-0.2.0.dist-info/METADATA
microstate-0.2.0.dist-info/WHEEL
microstate-0.2.0.dist-info/entry_points.txt
microstate-0.2.0.dist-info/top_level.txt
microstate-0.2.0.dist-info/RECORD
