Metadata-Version: 2.1
Name: microstate
Version: 0.2.0
Summary: Experimental standalone state storage service for crawlers at www.microprediction.org
Home-page: https://github.com/microprediction/microstate
Author: microprediction
Author-email: info@microprediction.org
License: MIT
Platform: UNKNOWN
Classifier: License :: OSI Approved :: MIT License
Classifier: Programming Language :: Python :: 3
Classifier: Programming Language :: Python :: 3.7
Classifier: Programming Language :: Python :: 3.8
Requires-Dist: microconventions (>=0.1.0)
Requires-Dist: redis
Requires-Dist: fakeredis
Requires-Dist: numpy
Requires-Dist: pathlib
Requires-Dist: requests
Requires-Dist: getjson
